code/ptdRegister.v
module register(input en, input [31:0] d, output reg [31:0] r);
always @(en) begin
  if (en)
    r <= d;
end
endmodule

module ptd(input clk, output ppulse);
  not  #2 P1(nclkd, clk);
  nand #2 P2(npulse, nclkd, clk);
  not  #2 P3(ppulse, npulse);
endmodule

module main;
reg [31:0] d;
wire [31:0] r;
reg clk;
wire en;

ptd ptd1(clk, en);
register register1(en, d, r);

initial begin
  clk = 0;
  d = 3;
  $monitor("%4dns monitor: clk=%d en=%d d=%d r=%d", $stime, clk, en, d, r);
  $dumpfile("ptdRegister.vcd"); // 輸出給 GTK wave 顯示波型
  $dumpvars;    
end

always #10 begin
  clk = clk + 1;
end

always #20 begin
  d = d + 1;
end

initial #300 $finish;

endmodule

code/ptdRegister.vcd
$date
	Mon Nov 25 16:20:04 2013
$end
$version
	Icarus Verilog
$end
$timescale
	1s
$end
$scope module main $end
$var wire 1 ! en $end
$var wire 32 " r [31:0] $end
$var reg 1 # clk $end
$var reg 32 $ d [31:0] $end
$scope module ptd1 $end
$var wire 1 % clk $end
$var wire 1 & nclkd $end
$var wire 1 ' npulse $end
$var wire 1 ! ppulse $end
$upscope $end
$scope module register1 $end
$var wire 32 ( d [31:0] $end
$var wire 1 ! en $end
$var reg 32 ) r [31:0] $end
$upscope $end
$upscope $end
$enddefinitions $end
#0
$dumpvars
bx )
b11 (
z'
z&
0%
b11 $
0#
bx "
z!
$end
#2
1'
1&
#4
0!
#10
1#
1%
#12
0&
0'
#14
b11 )
b11 "
1'
1!
#16
0!
#20
0#
0%
b100 $
b100 (
#22
1&
#30
1#
1%
#32
0&
0'
#34
b100 )
b100 "
1'
1!
#36
0!
#40
0#
0%
b101 $
b101 (
#42
1&
#50
1#
1%
#52
0&
0'
#54
b101 )
b101 "
1'
1!
#56
0!
#60
0#
0%
b110 $
b110 (
#62
1&
#70
1#
1%
#72
0&
0'
#74
b110 )
b110 "
1'
1!
#76
0!
#80
0#
0%
b111 $
b111 (
#82
1&
#90
1#
1%
#92
0&
0'
#94
b111 )
b111 "
1'
1!
#96
0!
#100
0#
0%
b1000 $
b1000 (
#102
1&
#110
1#
1%
#112
0&
0'
#114
b1000 )
b1000 "
1'
1!
#116
0!
#120
0#
0%
b1001 $
b1001 (
#122
1&
#130
1#
1%
#132
0&
0'
#134
b1001 )
b1001 "
1'
1!
#136
0!
#140
0#
0%
b1010 $
b1010 (
#142
1&
#150
1#
1%
#152
0&
0'
#154
b1010 )
b1010 "
1'
1!
#156
0!
#160
0#
0%
b1011 $
b1011 (
#162
1&
#170
1#
1%
#172
0&
0'
#174
b1011 )
b1011 "
1'
1!
#176
0!
#180
0#
0%
b1100 $
b1100 (
#182
1&
#190
1#
1%
#192
0&
0'
#194
b1100 )
b1100 "
1'
1!
#196
0!
#200
0#
0%
b1101 $
b1101 (
#202
1&
#210
1#
1%
#212
0&
0'
#214
b1101 )
b1101 "
1'
1!
#216
0!
#220
0#
0%
b1110 $
b1110 (
#222
1&
#230
1#
1%
#232
0&
0'
#234
b1110 )
b1110 "
1'
1!
#236
0!
#240
0#
0%
b1111 $
b1111 (
#242
1&
#250
1#
1%
#252
0&
0'
#254
b1111 )
b1111 "
1'
1!
#256
0!
#260
0#
0%
b10000 $
b10000 (
#262
1&
#270
1#
1%
#272
0&
0'
#274
b10000 )
b10000 "
1'
1!
#276
0!
#280
0#
0%
b10001 $
b10001 (
#282
1&
#290
1#
1%
#292
0&
0'
#294
b10001 )
b10001 "
1'
1!
#296
0!
#300
0#
0%
b10010 $
b10010 (
